odoo/addons/delivery_estimated_package_quantity_by_weight/README.rst
odoo/addons/delivery_estimated_package_quantity_by_weight/__init__.py
odoo/addons/delivery_estimated_package_quantity_by_weight/__manifest__.py
odoo/addons/delivery_estimated_package_quantity_by_weight/i18n/delivery_estimated_package_quantity_by_weight.pot
odoo/addons/delivery_estimated_package_quantity_by_weight/i18n/es.po
odoo/addons/delivery_estimated_package_quantity_by_weight/i18n/fr_BE.po
odoo/addons/delivery_estimated_package_quantity_by_weight/i18n/it.po
odoo/addons/delivery_estimated_package_quantity_by_weight/models/__init__.py
odoo/addons/delivery_estimated_package_quantity_by_weight/models/delivery_carrier.py
odoo/addons/delivery_estimated_package_quantity_by_weight/models/stock_picking.py
odoo/addons/delivery_estimated_package_quantity_by_weight/readme/CONTRIBUTORS.md
odoo/addons/delivery_estimated_package_quantity_by_weight/readme/DESCRIPTION.md
odoo/addons/delivery_estimated_package_quantity_by_weight/readme/USAGE.md
odoo/addons/delivery_estimated_package_quantity_by_weight/static/description/icon.png
odoo/addons/delivery_estimated_package_quantity_by_weight/static/description/index.html
odoo/addons/delivery_estimated_package_quantity_by_weight/tests/__init__.py
odoo/addons/delivery_estimated_package_quantity_by_weight/tests/test_stock_picking.py
odoo/addons/delivery_estimated_package_quantity_by_weight/views/delivery_carrier_views.xml
odoo/addons/delivery_estimated_package_quantity_by_weight/views/stock_picking_views.xml
odoo_addon_delivery_estimated_package_quantity_by_weight-18.0.1.0.0.2.dist-info/METADATA
odoo_addon_delivery_estimated_package_quantity_by_weight-18.0.1.0.0.2.dist-info/WHEEL
odoo_addon_delivery_estimated_package_quantity_by_weight-18.0.1.0.0.2.dist-info/top_level.txt
odoo_addon_delivery_estimated_package_quantity_by_weight-18.0.1.0.0.2.dist-info/RECORD
