Metadata-Version: 2.1
Name: odoo-addon-delivery_estimated_package_quantity_by_weight
Version: 18.0.1.0.0.2
Requires-Python: >=3.10
Requires-Dist: odoo==18.0.*
Summary: Compute the amount of packages a picking out should have depending on the weight of the products and the limit fixed by the carrier
Home-page: https://github.com/OCA/delivery-carrier
License: AGPL-3
Author: ACSONE SA/NV, Odoo Community Association (OCA)
Author-email: support@odoo-community.org
Classifier: Programming Language :: Python
Classifier: Framework :: Odoo
Classifier: Framework :: Odoo :: 18.0
Classifier: License :: OSI Approved :: GNU Affero General Public License v3
